<?xml version="1.0" encoding="UTF-8" standalone="yes"?>
<manifest>
  <control namespace="VFlow" constructor="UserInterface" version="0.0.1" display-name-key="UserInterface" description-key="UserInterface description" control-type="standard" api-version="1.3.18">
    <external-service-usage enabled="false"/>
    <data-set name="sampleDataSet" display-name-key="Dataset_Display_Key"/>
    <resources>
      <code path="index.ts" order="1"/>
      <css path="../styles/custom.css" order="1"/>
    </resources>
    <feature-usage/>
  </control>
</manifest>

